basicindex/__init__.py
basicindex/basic_index.cpython-312-darwin.so
basicindex-1.1.3.dist-info/METADATA
basicindex-1.1.3.dist-info/WHEEL
basicindex-1.1.3.dist-info/top_level.txt
basicindex-1.1.3.dist-info/RECORD
