Metadata-Version: 2.1
Name: basicindex
Version: 1.1.3
Summary: A Python package for handling basic indexing operations.
Classifier: Programming Language :: Python :: 3
Classifier: Programming Language :: Cython
Classifier: License :: OSI Approved :: MIT License
Classifier: Operating System :: OS Independent
Requires-Python: >=3.6
